tgcrypto.pypy37-pp73-x86-linux-gnu.so
tests/__init__.py
tests/cbc/test_cbc.py
tests/cbc/__init__.py
tests/ige/__init__.py
tests/ige/test_ige.py
tests/ctr/test_ctr.py
tests/ctr/__init__.py
Telecrypto-1.2.6.dist-info/NOTICE
Telecrypto-1.2.6.dist-info/COPYING.lesser
Telecrypto-1.2.6.dist-info/WHEEL
Telecrypto-1.2.6.dist-info/RECORD
Telecrypto-1.2.6.dist-info/COPYING
Telecrypto-1.2.6.dist-info/METADATA
Telecrypto-1.2.6.dist-info/top_level.txt
