Metadata-Version: 2.1
Name: Telecrypto
Version: 1.2.6
Summary: Fast and Portable Cryptography Extension Library for Pyrogram
Home-page: https://github.com/venombolteop
Download-URL: https://github.com/venombolteop/telecrypto/releases/latest
Author: venombolteop
Author-email: venombolteop@gmail.com
License: LGPLv3+
Project-URL: Tracker, https://github.com/venombolteop/telecrypto/issues
Project-URL: Community, https://t.me/pyrolink
Project-URL: Source, https://github.com/venombolteop/telecrypto
Project-URL: Documentation, https://docs.pyrogram.org
Keywords: pyrolink telegram crypto cryptography encryption mtproto extension library aes
Classifier: Development Status :: 5 - Production/Stable
Classifier: Intended Audience :: Developers
Classifier: License :: OSI Approved :: GNU Lesser General Public License v3 or later (LGPLv3+)
Classifier: Operating System :: OS Independent
Classifier: Programming Language :: C
Classifier: Programming Language :: Python
Classifier: Programming Language :: Python :: 3
Classifier: Programming Language :: Python :: 3.7
Classifier: Programming Language :: Python :: 3.8
Classifier: Programming Language :: Python :: 3.9
Classifier: Programming Language :: Python :: 3.10
Classifier: Programming Language :: Python :: 3.11
Classifier: Programming Language :: Python :: Implementation
Classifier: Programming Language :: Python :: Implementation :: CPython
Classifier: Programming Language :: Python :: Implementation :: PyPy
Classifier: Topic :: Security
Classifier: Topic :: Security :: Cryptography
Classifier: Topic :: Internet
Classifier: Topic :: Communications
Classifier: Topic :: Communications :: Chat
Classifier: Topic :: Software Development :: Libraries
Classifier: Topic :: Software Development :: Libraries :: Python Modules
Requires-Python: ~=3.7
License-File: COPYING
License-File: COPYING.lesser
License-File: NOTICE
